kahi_openalex_works/Kahi_openalex_works.py
kahi_openalex_works/__init__.py
kahi_openalex_works/_version.py
kahi_openalex_works/parser.py
kahi_openalex_works/process_one.py
Kahi_openalex_works-0.1.8.dist-info/LICENSE
Kahi_openalex_works-0.1.8.dist-info/METADATA
Kahi_openalex_works-0.1.8.dist-info/WHEEL
Kahi_openalex_works-0.1.8.dist-info/top_level.txt
Kahi_openalex_works-0.1.8.dist-info/RECORD
