Metadata-Version: 2.2
Name: Kahi_openalex_works
Version: 0.1.8
Summary: Kahi plugin to insert and update works from openalex
Home-page: https://github.com/colav/Kahi_plugins
Author: Colav
Author-email: colav@udea.edu.co
License: BSD
License-File: LICENSE
Requires-Dist: kahi
Requires-Dist: pymongo
Requires-Dist: joblib
Requires-Dist: kahi_impactu_utils>=0.0.10
Requires-Dist: mohan
Requires-Dist: thefuzz
Dynamic: author
Dynamic: author-email
Dynamic: description
Dynamic: description-content-type
Dynamic: home-page
Dynamic: license
Dynamic: requires-dist
Dynamic: summary
